cells/__init__.py
cells-0.1.0.dist-info/LICENSE
cells-0.1.0.dist-info/WHEEL
cells-0.1.0.dist-info/METADATA
cells-0.1.0.dist-info/RECORD
